clang_tidy_junit.py
clang_tidy_junit-0.5.1.dist-info/licenses/LICENSE
clang_tidy_junit-0.5.1.dist-info/METADATA
clang_tidy_junit-0.5.1.dist-info/WHEEL
clang_tidy_junit-0.5.1.dist-info/entry_points.txt
clang_tidy_junit-0.5.1.dist-info/top_level.txt
clang_tidy_junit-0.5.1.dist-info/RECORD
