Metadata-Version: 2.4
Name: clang-tidy-junit
Version: 0.5.1
Summary: Convert Clang-Tidy output to JUnit XML
License-Expression: MIT
Project-URL: Repository, https://github.com/nkr0/clang-tidy-junit
License-File: LICENSE
Requires-Dist: junitparser
Provides-Extra: dev
Requires-Dist: black; extra == "dev"
Requires-Dist: coverage; extra == "dev"
Requires-Dist: mypy; extra == "dev"
Requires-Dist: pylint; extra == "dev"
Dynamic: license-file
